{
  "gallery": {
    "modif": "padd",
    "count": "5",
    "items": [
      {
        "modif": "padd",
        "size": "sm",
        "items": [
          {
            "size": "sm",
            "src": "photo_1.jpg",
            "srcBig": "photo_1.jpg",
            "bsize": "cover",
            "modif": "padd",
            "bposition": "50% 50%",
            "name": "Rick and Morty",
            "lastseen": "just now",
            "socialLogo": "fb.png",
            "companyLogo": "rick-sanchez.png",
            "fullLink": "#",
            "tags": [
              "sanchez",
              "morty",
              "kicks",
              "blurb",
              "airblurb",
              "toon",
              "buz",
              "desperation",
              "wubba",
              "lubba",
              " left nipple",
              "bobo",
              "Looossseeerrrrr",
              "cronenbergs ",
              "babes"
            ],
            "about": [
              "Morty, can you get to the left nipple? If anything happened to you I would kill myself! I love you bad, bobo!",
              "Alan Rails, ladies and gentlemen. After his parents' tragic death in a railroad accident, he gained the power to summon ghost trains. It's not all bad though, they were spared having to see their grown son wear a whistle. These 2 halves don't belong together, bitch!"
            ]
          },
          {
            "size": "sm",
            "src": "photo_2.jpg",
            "srcBig": "photo_2.jpg",
            "bsize": "cover",
            "modif": "padd",
            "bposition": "50% 50%",
            "name": "Rick and Morty",
            "lastseen": "just now",
            "socialLogo": "fb.png",
            "companyLogo": "rick-sanchez.png",
            "fullLink": "#",
            "tags": [
              "sanchez",
              "morty",
              "kicks",
              "blurb",
              "airblurb",
              "toon",
              "buz",
              "desperation",
              "wubba",
              "lubba",
              " left nipple",
              "bobo",
              "Looossseeerrrrr",
              "cronenbergs ",
              "babes"
            ],
            "about": [
              "Morty, can you get to the left nipple? If anything happened to you I would kill myself! I love you bad, bobo!",
              "Alan Rails, ladies and gentlemen. After his parents' tragic death in a railroad accident, he gained the power to summon ghost trains. It's not all bad though, they were spared having to see their grown son wear a whistle. These 2 halves don't belong together, bitch!"
            ]
          }
        ]
      },
      {
        "modif": "padd",
        "size": "sm",
        "items": [
          {
            "size": "sm",
            "src": "photo_3.jpg",
            "srcBig": "photo_3.jpg",
            "bsize": "cover",
            "modif": "padd",
            "bposition": "50% 50%",
            "name": "Rick and Morty",
            "lastseen": "just now",
            "socialLogo": "fb.png",
            "companyLogo": "rick-sanchez.png",
            "fullLink": "#",
            "tags": [
              "sanchez",
              "morty",
              "kicks",
              "blurb",
              "airblurb",
              "toon",
              "buz",
              "desperation",
              "wubba",
              "lubba",
              " left nipple",
              "bobo",
              "Looossseeerrrrr",
              "cronenbergs ",
              "babes"
            ],
            "about": [
              "Morty, can you get to the left nipple? If anything happened to you I would kill myself! I love you bad, bobo!",
              "Alan Rails, ladies and gentlemen. After his parents' tragic death in a railroad accident, he gained the power to summon ghost trains. It's not all bad though, they were spared having to see their grown son wear a whistle. These 2 halves don't belong together, bitch!"
            ]
          },
          {
            "size": "sm",
            "src": "photo_4.jpg",
            "srcBig": "photo_4.jpg",
            "bsize": "cover",
            "modif": "padd",
            "bposition": "50% 50%",
            "name": "Rick and Morty",
            "lastseen": "just now",
            "socialLogo": "fb.png",
            "companyLogo": "rick-sanchez.png",
            "fullLink": "#",
            "tags": [
              "sanchez",
              "morty",
              "kicks",
              "blurb",
              "airblurb",
              "toon",
              "buz",
              "desperation",
              "wubba",
              "lubba",
              " left nipple",
              "bobo",
              "Looossseeerrrrr",
              "cronenbergs ",
              "babes"
            ],
            "about": [
              "Morty, can you get to the left nipple? If anything happened to you I would kill myself! I love you bad, bobo!",
              "Alan Rails, ladies and gentlemen. After his parents' tragic death in a railroad accident, he gained the power to summon ghost trains. It's not all bad though, they were spared having to see their grown son wear a whistle. These 2 halves don't belong together, bitch!"
            ]
          }
        ]
      },
      {
        "modif": "padd",
        "size": "sm",
        "items": [
          {
            "size": "sm",
            "src": "photo_5.jpg",
            "srcBig": "photo_5.jpg",
            "bsize": "cover",
            "modif": "padd",
            "bposition": "50% 50%",
            "name": "Rick and Morty",
            "lastseen": "just now",
            "socialLogo": "fb.png",
            "companyLogo": "rick-sanchez.png",
            "fullLink": "#",
            "tags": [
              "sanchez",
              "morty",
              "kicks",
              "blurb",
              "airblurb",
              "toon",
              "buz",
              "desperation",
              "wubba",
              "lubba",
              " left nipple",
              "bobo",
              "Looossseeerrrrr",
              "cronenbergs ",
              "babes"
            ],
            "about": [
              "Morty, can you get to the left nipple? If anything happened to you I would kill myself! I love you bad, bobo!",
              "Alan Rails, ladies and gentlemen. After his parents' tragic death in a railroad accident, he gained the power to summon ghost trains. It's not all bad though, they were spared having to see their grown son wear a whistle. These 2 halves don't belong together, bitch!"
            ]
          },
          {
            "size": "sm",
            "src": "photo_6.jpg",
            "srcBig": "photo_6.jpg",
            "bsize": "cover",
            "modif": "padd",
            "bposition": "50% 50%",
            "name": "Rick and Morty",
            "lastseen": "just now",
            "socialLogo": "fb.png",
            "companyLogo": "rick-sanchez.png",
            "fullLink": "#",
            "tags": [
              "sanchez",
              "morty",
              "kicks",
              "blurb",
              "airblurb",
              "toon",
              "buz",
              "desperation",
              "wubba",
              "lubba",
              " left nipple",
              "bobo",
              "Looossseeerrrrr",
              "cronenbergs ",
              "babes"
            ],
            "about": [
              "Morty, can you get to the left nipple? If anything happened to you I would kill myself! I love you bad, bobo!",
              "Alan Rails, ladies and gentlemen. After his parents' tragic death in a railroad accident, he gained the power to summon ghost trains. It's not all bad though, they were spared having to see their grown son wear a whistle. These 2 halves don't belong together, bitch!"
            ]
          }
        ]
      },
      {
        "modif": "padd",
        "size": "sm",
        "items": [
          {
            "size": "sm",
            "src": "photo_7.jpg",
            "srcBig": "photo_7.jpg",
            "bsize": "cover",
            "modif": "padd",
            "bposition": "50% 50%",
            "name": "Rick and Morty",
            "lastseen": "just now",
            "socialLogo": "fb.png",
            "companyLogo": "rick-sanchez.png",
            "fullLink": "#",
            "tags": [
              "sanchez",
              "morty",
              "kicks",
              "blurb",
              "airblurb",
              "toon",
              "buz",
              "desperation",
              "wubba",
              "lubba",
              " left nipple",
              "bobo",
              "Looossseeerrrrr",
              "cronenbergs ",
              "babes"
            ],
            "about": [
              "Morty, can you get to the left nipple? If anything happened to you I would kill myself! I love you bad, bobo!",
              "Alan Rails, ladies and gentlemen. After his parents' tragic death in a railroad accident, he gained the power to summon ghost trains. It's not all bad though, they were spared having to see their grown son wear a whistle. These 2 halves don't belong together, bitch!"
            ]
          },
          {
            "size": "sm",
            "src": "photo_8.jpg",
            "srcBig": "photo_8.jpg",
            "bsize": "cover",
            "modif": "padd",
            "bposition": "50% 50%",
            "name": "Rick and Morty",
            "lastseen": "just now",
            "socialLogo": "fb.png",
            "companyLogo": "rick-sanchez.png",
            "fullLink": "#",
            "tags": [
              "sanchez",
              "morty",
              "kicks",
              "blurb",
              "airblurb",
              "toon",
              "buz",
              "desperation",
              "wubba",
              "lubba",
              " left nipple",
              "bobo",
              "Looossseeerrrrr",
              "cronenbergs ",
              "babes"
            ],
            "about": [
              "Morty, can you get to the left nipple? If anything happened to you I would kill myself! I love you bad, bobo!",
              "Alan Rails, ladies and gentlemen. After his parents' tragic death in a railroad accident, he gained the power to summon ghost trains. It's not all bad though, they were spared having to see their grown son wear a whistle. These 2 halves don't belong together, bitch!"
            ]
          }
        ]
      },
      {
        "modif": "padd",
        "size": "sm",
        "items": [
          {
            "size": "sm",
            "src": "photo_9.jpg",
            "srcBig": "photo_9.jpg",
            "bsize": "cover",
            "modif": "padd",
            "bposition": "50% 50%",
            "name": "Rick and Morty",
            "lastseen": "just now",
            "socialLogo": "fb.png",
            "companyLogo": "rick-sanchez.png",
            "fullLink": "#",
            "tags": [
              "sanchez",
              "morty",
              "kicks",
              "blurb",
              "airblurb",
              "toon",
              "buz",
              "desperation",
              "wubba",
              "lubba",
              " left nipple",
              "bobo",
              "Looossseeerrrrr",
              "cronenbergs ",
              "babes"
            ],
            "about": [
              "Morty, can you get to the left nipple? If anything happened to you I would kill myself! I love you bad, bobo!",
              "Alan Rails, ladies and gentlemen. After his parents' tragic death in a railroad accident, he gained the power to summon ghost trains. It's not all bad though, they were spared having to see their grown son wear a whistle. These 2 halves don't belong together, bitch!"
            ]
          },
          {
            "size": "sm",
            "src": "photo_10.jpg",
            "srcBig": "photo_10.jpg",
            "bsize": "cover",
            "modif": "padd",
            "bposition": "50% 50%",
            "name": "Rick and Morty",
            "lastseen": "just now",
            "socialLogo": "fb.png",
            "companyLogo": "rick-sanchez.png",
            "fullLink": "#",
            "tags": [
              "sanchez",
              "morty",
              "kicks",
              "blurb",
              "airblurb",
              "toon",
              "buz",
              "desperation",
              "wubba",
              "lubba",
              " left nipple",
              "bobo",
              "Looossseeerrrrr",
              "cronenbergs ",
              "babes"
            ],
            "about": [
              "Morty, can you get to the left nipple? If anything happened to you I would kill myself! I love you bad, bobo!",
              "Alan Rails, ladies and gentlemen. After his parents' tragic death in a railroad accident, he gained the power to summon ghost trains. It's not all bad though, they were spared having to see their grown son wear a whistle. These 2 halves don't belong together, bitch!"
            ]
          }
        ]
      },
      {
        "modif": "padd",
        "size": "sm",
        "items": [
          {
            "size": "sm",
            "src": "photo_11.jpg",
            "srcBig": "photo_11.jpg",
            "bsize": "cover",
            "modif": "padd",
            "bposition": "50% 50%",
            "name": "Rick and Morty",
            "lastseen": "just now",
            "socialLogo": "fb.png",
            "companyLogo": "rick-sanchez.png",
            "fullLink": "#",
            "tags": [
              "sanchez",
              "morty",
              "kicks",
              "blurb",
              "airblurb",
              "toon",
              "buz",
              "desperation",
              "wubba",
              "lubba",
              " left nipple",
              "bobo",
              "Looossseeerrrrr",
              "cronenbergs ",
              "babes"
            ],
            "about": [
              "Morty, can you get to the left nipple? If anything happened to you I would kill myself! I love you bad, bobo!",
              "Alan Rails, ladies and gentlemen. After his parents' tragic death in a railroad accident, he gained the power to summon ghost trains. It's not all bad though, they were spared having to see their grown son wear a whistle. These 2 halves don't belong together, bitch!"
            ]
          },
          {
            "size": "sm",
            "src": "photo_12.jpg",
            "srcBig": "photo_12.jpg",
            "bsize": "cover",
            "modif": "padd",
            "bposition": "50% 50%",
            "name": "Rick and Morty",
            "lastseen": "just now",
            "socialLogo": "fb.png",
            "companyLogo": "rick-sanchez.png",
            "fullLink": "#",
            "tags": [
              "sanchez",
              "morty",
              "kicks",
              "blurb",
              "airblurb",
              "toon",
              "buz",
              "desperation",
              "wubba",
              "lubba",
              " left nipple",
              "bobo",
              "Looossseeerrrrr",
              "cronenbergs ",
              "babes"
            ],
            "about": [
              "Morty, can you get to the left nipple? If anything happened to you I would kill myself! I love you bad, bobo!",
              "Alan Rails, ladies and gentlemen. After his parents' tragic death in a railroad accident, he gained the power to summon ghost trains. It's not all bad though, they were spared having to see their grown son wear a whistle. These 2 halves don't belong together, bitch!"
            ]
          }
        ]
      },
      {
        "modif": "padd",
        "size": "sm",
        "items": [
          {
            "size": "sm",
            "src": "photo_13.jpg",
            "srcBig": "photo_13.jpg",
            "bsize": "cover",
            "modif": "padd",
            "bposition": "50% 50%",
            "name": "Rick and Morty",
            "lastseen": "just now",
            "socialLogo": "fb.png",
            "companyLogo": "rick-sanchez.png",
            "fullLink": "#",
            "tags": [
              "sanchez",
              "morty",
              "kicks",
              "blurb",
              "airblurb",
              "toon",
              "buz",
              "desperation",
              "wubba",
              "lubba",
              " left nipple",
              "bobo",
              "Looossseeerrrrr",
              "cronenbergs ",
              "babes"
            ],
            "about": [
              "Morty, can you get to the left nipple? If anything happened to you I would kill myself! I love you bad, bobo!",
              "Alan Rails, ladies and gentlemen. After his parents' tragic death in a railroad accident, he gained the power to summon ghost trains. It's not all bad though, they were spared having to see their grown son wear a whistle. These 2 halves don't belong together, bitch!"
            ]
          },
          {
            "size": "sm",
            "src": "photo_14.jpg",
            "srcBig": "photo_14.jpg",
            "bsize": "cover",
            "modif": "padd",
            "bposition": "50% 50%",
            "name": "Rick and Morty",
            "lastseen": "just now",
            "socialLogo": "fb.png",
            "companyLogo": "rick-sanchez.png",
            "fullLink": "#",
            "tags": [
              "sanchez",
              "morty",
              "kicks",
              "blurb",
              "airblurb",
              "toon",
              "buz",
              "desperation",
              "wubba",
              "lubba",
              " left nipple",
              "bobo",
              "Looossseeerrrrr",
              "cronenbergs ",
              "babes"
            ],
            "about": [
              "Morty, can you get to the left nipple? If anything happened to you I would kill myself! I love you bad, bobo!",
              "Alan Rails, ladies and gentlemen. After his parents' tragic death in a railroad accident, he gained the power to summon ghost trains. It's not all bad though, they were spared having to see their grown son wear a whistle. These 2 halves don't belong together, bitch!"
            ]
          }
        ]
      },
      {
        "modif": "padd",
        "size": "sm",
        "items": [
          {
            "size": "sm",
            "src": "photo_15.jpg",
            "srcBig": "photo_15.jpg",
            "bsize": "cover",
            "modif": "padd",
            "bposition": "50% 50%",
            "name": "Rick and Morty",
            "lastseen": "just now",
            "socialLogo": "fb.png",
            "companyLogo": "rick-sanchez.png",
            "fullLink": "#",
            "tags": [
              "sanchez",
              "morty",
              "kicks",
              "blurb",
              "airblurb",
              "toon",
              "buz",
              "desperation",
              "wubba",
              "lubba",
              " left nipple",
              "bobo",
              "Looossseeerrrrr",
              "cronenbergs ",
              "babes"
            ],
            "about": [
              "Morty, can you get to the left nipple? If anything happened to you I would kill myself! I love you bad, bobo!",
              "Alan Rails, ladies and gentlemen. After his parents' tragic death in a railroad accident, he gained the power to summon ghost trains. It's not all bad though, they were spared having to see their grown son wear a whistle. These 2 halves don't belong together, bitch!"
            ]
          },
          {
            "size": "sm",
            "src": "photo_1.jpg",
            "srcBig": "photo_1.jpg",
            "bsize": "cover",
            "modif": "padd",
            "bposition": "50% 50%",
            "name": "Rick and Morty",
            "lastseen": "just now",
            "socialLogo": "fb.png",
            "companyLogo": "rick-sanchez.png",
            "fullLink": "#",
            "tags": [
              "sanchez",
              "morty",
              "kicks",
              "blurb",
              "airblurb",
              "toon",
              "buz",
              "desperation",
              "wubba",
              "lubba",
              " left nipple",
              "bobo",
              "Looossseeerrrrr",
              "cronenbergs ",
              "babes"
            ],
            "about": [
              "Morty, can you get to the left nipple? If anything happened to you I would kill myself! I love you bad, bobo!",
              "Alan Rails, ladies and gentlemen. After his parents' tragic death in a railroad accident, he gained the power to summon ghost trains. It's not all bad though, they were spared having to see their grown son wear a whistle. These 2 halves don't belong together, bitch!"
            ]
          }
        ]
      },
      {
        "modif": "padd",
        "size": "sm",
        "items": [
          {
            "size": "sm",
            "src": "photo_2.jpg",
            "srcBig": "photo_2.jpg",
            "bsize": "cover",
            "modif": "padd",
            "bposition": "50% 50%",
            "name": "Rick and Morty",
            "lastseen": "just now",
            "socialLogo": "fb.png",
            "companyLogo": "rick-sanchez.png",
            "fullLink": "#",
            "tags": [
              "sanchez",
              "morty",
              "kicks",
              "blurb",
              "airblurb",
              "toon",
              "buz",
              "desperation",
              "wubba",
              "lubba",
              " left nipple",
              "bobo",
              "Looossseeerrrrr",
              "cronenbergs ",
              "babes"
            ],
            "about": [
              "Morty, can you get to the left nipple? If anything happened to you I would kill myself! I love you bad, bobo!",
              "Alan Rails, ladies and gentlemen. After his parents' tragic death in a railroad accident, he gained the power to summon ghost trains. It's not all bad though, they were spared having to see their grown son wear a whistle. These 2 halves don't belong together, bitch!"
            ]
          },
          {
            "size": "sm",
            "src": "photo_3.jpg",
            "srcBig": "photo_3.jpg",
            "bsize": "cover",
            "modif": "padd",
            "bposition": "50% 50%",
            "name": "Rick and Morty",
            "lastseen": "just now",
            "socialLogo": "fb.png",
            "companyLogo": "rick-sanchez.png",
            "fullLink": "#",
            "tags": [
              "sanchez",
              "morty",
              "kicks",
              "blurb",
              "airblurb",
              "toon",
              "buz",
              "desperation",
              "wubba",
              "lubba",
              " left nipple",
              "bobo",
              "Looossseeerrrrr",
              "cronenbergs ",
              "babes"
            ],
            "about": [
              "Morty, can you get to the left nipple? If anything happened to you I would kill myself! I love you bad, bobo!",
              "Alan Rails, ladies and gentlemen. After his parents' tragic death in a railroad accident, he gained the power to summon ghost trains. It's not all bad though, they were spared having to see their grown son wear a whistle. These 2 halves don't belong together, bitch!"
            ]
          }
        ]
      },
      {
        "modif": "padd",
        "size": "sm",
        "items": [
          {
            "size": "sm",
            "src": "photo_4.jpg",
            "srcBig": "photo_4.jpg",
            "bsize": "cover",
            "modif": "padd",
            "bposition": "50% 50%",
            "name": "Rick and Morty",
            "lastseen": "just now",
            "socialLogo": "fb.png",
            "companyLogo": "rick-sanchez.png",
            "fullLink": "#",
            "tags": [
              "sanchez",
              "morty",
              "kicks",
              "blurb",
              "airblurb",
              "toon",
              "buz",
              "desperation",
              "wubba",
              "lubba",
              " left nipple",
              "bobo",
              "Looossseeerrrrr",
              "cronenbergs ",
              "babes"
            ],
            "about": [
              "Morty, can you get to the left nipple? If anything happened to you I would kill myself! I love you bad, bobo!",
              "Alan Rails, ladies and gentlemen. After his parents' tragic death in a railroad accident, he gained the power to summon ghost trains. It's not all bad though, they were spared having to see their grown son wear a whistle. These 2 halves don't belong together, bitch!"
            ]
          },
          {
            "size": "sm",
            "src": "photo_5.jpg",
            "srcBig": "photo_5.jpg",
            "bsize": "cover",
            "modif": "padd",
            "bposition": "50% 50%",
            "name": "Rick and Morty",
            "lastseen": "just now",
            "socialLogo": "fb.png",
            "companyLogo": "rick-sanchez.png",
            "fullLink": "#",
            "tags": [
              "sanchez",
              "morty",
              "kicks",
              "blurb",
              "airblurb",
              "toon",
              "buz",
              "desperation",
              "wubba",
              "lubba",
              " left nipple",
              "bobo",
              "Looossseeerrrrr",
              "cronenbergs ",
              "babes"
            ],
            "about": [
              "Morty, can you get to the left nipple? If anything happened to you I would kill myself! I love you bad, bobo!",
              "Alan Rails, ladies and gentlemen. After his parents' tragic death in a railroad accident, he gained the power to summon ghost trains. It's not all bad though, they were spared having to see their grown son wear a whistle. These 2 halves don't belong together, bitch!"
            ]
          }
        ]
      },
      {
        "modif": "padd",
        "size": "sm",
        "items": [
          {
            "size": "sm",
            "src": "photo_6.jpg",
            "srcBig": "photo_6.jpg",
            "bsize": "cover",
            "modif": "padd",
            "bposition": "50% 50%",
            "name": "Rick and Morty",
            "lastseen": "just now",
            "socialLogo": "fb.png",
            "companyLogo": "rick-sanchez.png",
            "fullLink": "#",
            "tags": [
              "sanchez",
              "morty",
              "kicks",
              "blurb",
              "airblurb",
              "toon",
              "buz",
              "desperation",
              "wubba",
              "lubba",
              " left nipple",
              "bobo",
              "Looossseeerrrrr",
              "cronenbergs ",
              "babes"
            ],
            "about": [
              "Morty, can you get to the left nipple? If anything happened to you I would kill myself! I love you bad, bobo!",
              "Alan Rails, ladies and gentlemen. After his parents' tragic death in a railroad accident, he gained the power to summon ghost trains. It's not all bad though, they were spared having to see their grown son wear a whistle. These 2 halves don't belong together, bitch!"
            ]
          },
          {
            "size": "sm",
            "src": "photo_7.jpg",
            "srcBig": "photo_7.jpg",
            "bsize": "cover",
            "modif": "padd",
            "bposition": "50% 50%",
            "name": "Rick and Morty",
            "lastseen": "just now",
            "socialLogo": "fb.png",
            "companyLogo": "rick-sanchez.png",
            "fullLink": "#",
            "tags": [
              "sanchez",
              "morty",
              "kicks",
              "blurb",
              "airblurb",
              "toon",
              "buz",
              "desperation",
              "wubba",
              "lubba",
              " left nipple",
              "bobo",
              "Looossseeerrrrr",
              "cronenbergs ",
              "babes"
            ],
            "about": [
              "Morty, can you get to the left nipple? If anything happened to you I would kill myself! I love you bad, bobo!",
              "Alan Rails, ladies and gentlemen. After his parents' tragic death in a railroad accident, he gained the power to summon ghost trains. It's not all bad though, they were spared having to see their grown son wear a whistle. These 2 halves don't belong together, bitch!"
            ]
          }
        ]
      },
      {
        "modif": "padd",
        "size": "sm",
        "items": [
          {
            "size": "sm",
            "src": "photo_8.jpg",
            "srcBig": "photo_8.jpg",
            "bsize": "cover",
            "modif": "padd",
            "bposition": "50% 50%",
            "name": "Rick and Morty",
            "lastseen": "just now",
            "socialLogo": "fb.png",
            "companyLogo": "rick-sanchez.png",
            "fullLink": "#",
            "tags": [
              "sanchez",
              "morty",
              "kicks",
              "blurb",
              "airblurb",
              "toon",
              "buz",
              "desperation",
              "wubba",
              "lubba",
              " left nipple",
              "bobo",
              "Looossseeerrrrr",
              "cronenbergs ",
              "babes"
            ],
            "about": [
              "Morty, can you get to the left nipple? If anything happened to you I would kill myself! I love you bad, bobo!",
              "Alan Rails, ladies and gentlemen. After his parents' tragic death in a railroad accident, he gained the power to summon ghost trains. It's not all bad though, they were spared having to see their grown son wear a whistle. These 2 halves don't belong together, bitch!"
            ]
          },
          {
            "size": "sm",
            "src": "photo_9.jpg",
            "srcBig": "photo_9.jpg",
            "bsize": "cover",
            "modif": "padd",
            "bposition": "50% 50%",
            "name": "Rick and Morty",
            "lastseen": "just now",
            "socialLogo": "fb.png",
            "companyLogo": "rick-sanchez.png",
            "fullLink": "#",
            "tags": [
              "sanchez",
              "morty",
              "kicks",
              "blurb",
              "airblurb",
              "toon",
              "buz",
              "desperation",
              "wubba",
              "lubba",
              " left nipple",
              "bobo",
              "Looossseeerrrrr",
              "cronenbergs ",
              "babes"
            ],
            "about": [
              "Morty, can you get to the left nipple? If anything happened to you I would kill myself! I love you bad, bobo!",
              "Alan Rails, ladies and gentlemen. After his parents' tragic death in a railroad accident, he gained the power to summon ghost trains. It's not all bad though, they were spared having to see their grown son wear a whistle. These 2 halves don't belong together, bitch!"
            ]
          }
        ]
      },
      {
        "modif": "padd",
        "size": "sm",
        "items": [
          {
            "size": "sm",
            "src": "photo_10.jpg",
            "srcBig": "photo_10.jpg",
            "bsize": "cover",
            "modif": "padd",
            "bposition": "50% 50%",
            "name": "Rick and Morty",
            "lastseen": "just now",
            "socialLogo": "fb.png",
            "companyLogo": "rick-sanchez.png",
            "fullLink": "#",
            "tags": [
              "sanchez",
              "morty",
              "kicks",
              "blurb",
              "airblurb",
              "toon",
              "buz",
              "desperation",
              "wubba",
              "lubba",
              " left nipple",
              "bobo",
              "Looossseeerrrrr",
              "cronenbergs ",
              "babes"
            ],
            "about": [
              "Morty, can you get to the left nipple? If anything happened to you I would kill myself! I love you bad, bobo!",
              "Alan Rails, ladies and gentlemen. After his parents' tragic death in a railroad accident, he gained the power to summon ghost trains. It's not all bad though, they were spared having to see their grown son wear a whistle. These 2 halves don't belong together, bitch!"
            ]
          },
          {
            "size": "sm",
            "src": "photo_11.jpg",
            "srcBig": "photo_11.jpg",
            "bsize": "cover",
            "modif": "padd",
            "bposition": "50% 50%",
            "name": "Rick and Morty",
            "lastseen": "just now",
            "socialLogo": "fb.png",
            "companyLogo": "rick-sanchez.png",
            "fullLink": "#",
            "tags": [
              "sanchez",
              "morty",
              "kicks",
              "blurb",
              "airblurb",
              "toon",
              "buz",
              "desperation",
              "wubba",
              "lubba",
              " left nipple",
              "bobo",
              "Looossseeerrrrr",
              "cronenbergs ",
              "babes"
            ],
            "about": [
              "Morty, can you get to the left nipple? If anything happened to you I would kill myself! I love you bad, bobo!",
              "Alan Rails, ladies and gentlemen. After his parents' tragic death in a railroad accident, he gained the power to summon ghost trains. It's not all bad though, they were spared having to see their grown son wear a whistle. These 2 halves don't belong together, bitch!"
            ]
          }
        ]
      },
      {
        "modif": "padd",
        "size": "sm",
        "items": [
          {
            "size": "sm",
            "src": "photo_12.jpg",
            "srcBig": "photo_12.jpg",
            "bsize": "cover",
            "modif": "padd",
            "bposition": "50% 50%",
            "name": "Rick and Morty",
            "lastseen": "just now",
            "socialLogo": "fb.png",
            "companyLogo": "rick-sanchez.png",
            "fullLink": "#",
            "tags": [
              "sanchez",
              "morty",
              "kicks",
              "blurb",
              "airblurb",
              "toon",
              "buz",
              "desperation",
              "wubba",
              "lubba",
              " left nipple",
              "bobo",
              "Looossseeerrrrr",
              "cronenbergs ",
              "babes"
            ],
            "about": [
              "Morty, can you get to the left nipple? If anything happened to you I would kill myself! I love you bad, bobo!",
              "Alan Rails, ladies and gentlemen. After his parents' tragic death in a railroad accident, he gained the power to summon ghost trains. It's not all bad though, they were spared having to see their grown son wear a whistle. These 2 halves don't belong together, bitch!"
            ]
          },
          {
            "size": "sm",
            "src": "photo_13.jpg",
            "srcBig": "photo_13.jpg",
            "bsize": "cover",
            "modif": "padd",
            "bposition": "50% 50%",
            "name": "Rick and Morty",
            "lastseen": "just now",
            "socialLogo": "fb.png",
            "companyLogo": "rick-sanchez.png",
            "fullLink": "#",
            "tags": [
              "sanchez",
              "morty",
              "kicks",
              "blurb",
              "airblurb",
              "toon",
              "buz",
              "desperation",
              "wubba",
              "lubba",
              " left nipple",
              "bobo",
              "Looossseeerrrrr",
              "cronenbergs ",
              "babes"
            ],
            "about": [
              "Morty, can you get to the left nipple? If anything happened to you I would kill myself! I love you bad, bobo!",
              "Alan Rails, ladies and gentlemen. After his parents' tragic death in a railroad accident, he gained the power to summon ghost trains. It's not all bad though, they were spared having to see their grown son wear a whistle. These 2 halves don't belong together, bitch!"
            ]
          }
        ]
      },
      {
        "modif": "padd",
        "size": "sm",
        "items": [
          {
            "size": "sm",
            "src": "photo_14.jpg",
            "srcBig": "photo_14.jpg",
            "bsize": "cover",
            "modif": "padd",
            "bposition": "50% 50%",
            "name": "Rick and Morty",
            "lastseen": "just now",
            "socialLogo": "fb.png",
            "companyLogo": "rick-sanchez.png",
            "fullLink": "#",
            "tags": [
              "sanchez",
              "morty",
              "kicks",
              "blurb",
              "airblurb",
              "toon",
              "buz",
              "desperation",
              "wubba",
              "lubba",
              " left nipple",
              "bobo",
              "Looossseeerrrrr",
              "cronenbergs ",
              "babes"
            ],
            "about": [
              "Morty, can you get to the left nipple? If anything happened to you I would kill myself! I love you bad, bobo!",
              "Alan Rails, ladies and gentlemen. After his parents' tragic death in a railroad accident, he gained the power to summon ghost trains. It's not all bad though, they were spared having to see their grown son wear a whistle. These 2 halves don't belong together, bitch!"
            ]
          },
          {
            "size": "sm",
            "src": "photo_15.jpg",
            "srcBig": "photo_15.jpg",
            "bsize": "cover",
            "modif": "padd",
            "bposition": "50% 50%",
            "name": "Rick and Morty",
            "lastseen": "just now",
            "socialLogo": "fb.png",
            "companyLogo": "rick-sanchez.png",
            "fullLink": "#",
            "tags": [
              "sanchez",
              "morty",
              "kicks",
              "blurb",
              "airblurb",
              "toon",
              "buz",
              "desperation",
              "wubba",
              "lubba",
              " left nipple",
              "bobo",
              "Looossseeerrrrr",
              "cronenbergs ",
              "babes"
            ],
            "about": [
              "Morty, can you get to the left nipple? If anything happened to you I would kill myself! I love you bad, bobo!",
              "Alan Rails, ladies and gentlemen. After his parents' tragic death in a railroad accident, he gained the power to summon ghost trains. It's not all bad though, they were spared having to see their grown son wear a whistle. These 2 halves don't belong together, bitch!"
            ]
          }
        ]
      },
      {
        "modif": "padd",
        "size": "sm",
        "items": [
          {
            "size": "sm",
            "src": "photo_2.jpg",
            "srcBig": "photo_2.jpg",
            "bsize": "cover",
            "modif": "padd",
            "bposition": "50% 50%",
            "name": "Rick and Morty",
            "lastseen": "just now",
            "socialLogo": "fb.png",
            "companyLogo": "rick-sanchez.png",
            "fullLink": "#",
            "tags": [
              "sanchez",
              "morty",
              "kicks",
              "blurb",
              "airblurb",
              "toon",
              "buz",
              "desperation",
              "wubba",
              "lubba",
              " left nipple",
              "bobo",
              "Looossseeerrrrr",
              "cronenbergs ",
              "babes"
            ],
            "about": [
              "Morty, can you get to the left nipple? If anything happened to you I would kill myself! I love you bad, bobo!",
              "Alan Rails, ladies and gentlemen. After his parents' tragic death in a railroad accident, he gained the power to summon ghost trains. It's not all bad though, they were spared having to see their grown son wear a whistle. These 2 halves don't belong together, bitch!"
            ]
          },
          {
            "size": "sm",
            "src": "photo_12.jpg",
            "srcBig": "photo_12.jpg",
            "bsize": "cover",
            "modif": "padd",
            "bposition": "50% 50%",
            "name": "Rick and Morty",
            "lastseen": "just now",
            "socialLogo": "fb.png",
            "companyLogo": "rick-sanchez.png",
            "fullLink": "#",
            "tags": [
              "sanchez",
              "morty",
              "kicks",
              "blurb",
              "airblurb",
              "toon",
              "buz",
              "desperation",
              "wubba",
              "lubba",
              " left nipple",
              "bobo",
              "Looossseeerrrrr",
              "cronenbergs ",
              "babes"
            ],
            "about": [
              "Morty, can you get to the left nipple? If anything happened to you I would kill myself! I love you bad, bobo!",
              "Alan Rails, ladies and gentlemen. After his parents' tragic death in a railroad accident, he gained the power to summon ghost trains. It's not all bad though, they were spared having to see their grown son wear a whistle. These 2 halves don't belong together, bitch!"
            ]
          }
        ]
      },
      {
        "modif": "padd",
        "size": "sm",
        "items": [
          {
            "size": "sm",
            "src": "photo_6.jpg",
            "srcBig": "photo_6.jpg",
            "bsize": "cover",
            "modif": "padd",
            "bposition": "50% 50%",
            "name": "Rick and Morty",
            "lastseen": "just now",
            "socialLogo": "fb.png",
            "companyLogo": "rick-sanchez.png",
            "fullLink": "#",
            "tags": [
              "sanchez",
              "morty",
              "kicks",
              "blurb",
              "airblurb",
              "toon",
              "buz",
              "desperation",
              "wubba",
              "lubba",
              " left nipple",
              "bobo",
              "Looossseeerrrrr",
              "cronenbergs ",
              "babes"
            ],
            "about": [
              "Morty, can you get to the left nipple? If anything happened to you I would kill myself! I love you bad, bobo!",
              "Alan Rails, ladies and gentlemen. After his parents' tragic death in a railroad accident, he gained the power to summon ghost trains. It's not all bad though, they were spared having to see their grown son wear a whistle. These 2 halves don't belong together, bitch!"
            ]
          },
          {
            "size": "sm",
            "src": "photo_7.jpg",
            "srcBig": "photo_7.jpg",
            "bsize": "cover",
            "modif": "padd",
            "bposition": "50% 50%",
            "name": "Rick and Morty",
            "lastseen": "just now",
            "socialLogo": "fb.png",
            "companyLogo": "rick-sanchez.png",
            "fullLink": "#",
            "tags": [
              "sanchez",
              "morty",
              "kicks",
              "blurb",
              "airblurb",
              "toon",
              "buz",
              "desperation",
              "wubba",
              "lubba",
              " left nipple",
              "bobo",
              "Looossseeerrrrr",
              "cronenbergs ",
              "babes"
            ],
            "about": [
              "Morty, can you get to the left nipple? If anything happened to you I would kill myself! I love you bad, bobo!",
              "Alan Rails, ladies and gentlemen. After his parents' tragic death in a railroad accident, he gained the power to summon ghost trains. It's not all bad though, they were spared having to see their grown son wear a whistle. These 2 halves don't belong together, bitch!"
            ]
          }
        ]
      },
      {
        "modif": "padd",
        "size": "sm",
        "items": [
          {
            "size": "sm",
            "src": "photo_8.jpg",
            "srcBig": "photo_8.jpg",
            "bsize": "cover",
            "modif": "padd",
            "bposition": "50% 50%",
            "name": "Rick and Morty",
            "lastseen": "just now",
            "socialLogo": "fb.png",
            "companyLogo": "rick-sanchez.png",
            "fullLink": "#",
            "tags": [
              "sanchez",
              "morty",
              "kicks",
              "blurb",
              "airblurb",
              "toon",
              "buz",
              "desperation",
              "wubba",
              "lubba",
              " left nipple",
              "bobo",
              "Looossseeerrrrr",
              "cronenbergs ",
              "babes"
            ],
            "about": [
              "Morty, can you get to the left nipple? If anything happened to you I would kill myself! I love you bad, bobo!",
              "Alan Rails, ladies and gentlemen. After his parents' tragic death in a railroad accident, he gained the power to summon ghost trains. It's not all bad though, they were spared having to see their grown son wear a whistle. These 2 halves don't belong together, bitch!"
            ]
          },
          {
            "size": "sm",
            "src": "photo_3.jpg",
            "srcBig": "photo_3.jpg",
            "bsize": "cover",
            "modif": "padd",
            "bposition": "50% 50%",
            "name": "Rick and Morty",
            "lastseen": "just now",
            "socialLogo": "fb.png",
            "companyLogo": "rick-sanchez.png",
            "fullLink": "#",
            "tags": [
              "sanchez",
              "morty",
              "kicks",
              "blurb",
              "airblurb",
              "toon",
              "buz",
              "desperation",
              "wubba",
              "lubba",
              " left nipple",
              "bobo",
              "Looossseeerrrrr",
              "cronenbergs ",
              "babes"
            ],
            "about": [
              "Morty, can you get to the left nipple? If anything happened to you I would kill myself! I love you bad, bobo!",
              "Alan Rails, ladies and gentlemen. After his parents' tragic death in a railroad accident, he gained the power to summon ghost trains. It's not all bad though, they were spared having to see their grown son wear a whistle. These 2 halves don't belong together, bitch!"
            ]
          }
        ]
      }
    ]
  }
}
